{
  "version": 1,
  "base_track": "蛙化現象に悩んでる女の子の話。",
  "base_artist": "りりあ。",
  "createdAt": "2025-12-15T02:37:09.489549Z",
  "candidates": [
    {
      "id": "lrclib_1",
      "source": "lrclib",
      "title": "蛙化現象に悩んでる女の子の話。",
      "artist": "りりあ。",
      "has_synced": true,
      "path": "select/01_蛙化現象に悩んでる女の子の話。_りりあ。.lrc"
    },
    {
      "id": "lrclib_2",
      "source": "lrclib",
      "title": "蛙化現象に悩んでる女の子の話。",
      "artist": "Riria",
      "has_synced": true,
      "path": "select/02_蛙化現象に悩んでる女の子の話。_Riria.lrc"
    },
    {
      "id": "lrclib_3",
      "source": "lrclib",
      "title": "蛙化現象に悩んでる女の子の話。",
      "artist": "りりあ。",
      "has_synced": true,
      "path": "select/03_蛙化現象に悩んでる女の子の話。_りりあ。.lrc"
    },
    {
      "id": "lrclib_4",
      "source": "lrclib",
      "title": "りりあ。riria. / 蛙化現象に悩んでる女の子の話。 [Music Video]",
      "artist": "りりあ。",
      "has_synced": true,
      "path": "select/04_りりあ。riria.___蛙化現象に悩んでる女の子の話。_[Music_Video]_りりあ。.lrc"
    },
    {
      "id": "petitlyrics_1",
      "source": "petitlyrics",
      "title": "蛙化現象に悩んでる女の子の話。",
      "artist": "りりあ。",
      "has_synced": false,
      "path": "select/pl_01_蛙化現象に悩んでる女の子の話。_りりあ。.txt"
    }
  ]
}